cap3d_viz/__init__.py
cap3d_viz/data_models.py
cap3d_viz/parser.py
cap3d_viz/test_refactored.py
cap3d_viz/utils.py
cap3d_viz/visualizer.py
cap3d_viz-1.2.1.dist-info/licenses/LICENSE
cap3d_viz-1.2.1.dist-info/METADATA
cap3d_viz-1.2.1.dist-info/WHEEL
cap3d_viz-1.2.1.dist-info/entry_points.txt
cap3d_viz-1.2.1.dist-info/top_level.txt
cap3d_viz-1.2.1.dist-info/RECORD
