Metadata-Version: 2.4
Name: cap3d-viz
Version: 1.2.1
Summary: High-Performance 3D Visualization for CAP3D Files
Home-page: https://github.com/andykofman/RWCap_view
Author: Ahmed Ali
Author-email: Ahmed Ali <ali.a@aucegypt.edu>
Maintainer-email: Ahmed Ali <ali.a@aucegypt.edu>
License: MIT License
Project-URL: Homepage, https://github.com/andykofman/RWCap_view
Project-URL: Documentation, https://cap3d-viz.readthedocs.io/
Project-URL: Repository, https://github.com/andykofman/RWCap_view
Project-URL: Issues, https://github.com/andykofman/RWCap_view/issues
Keywords: 3D visualization,CAP3D,capacitance,integrated circuits,EDA,scientific computing,plotly,parsing,state machine
Classifier: Development Status :: 5 - Production/Stable
Classifier: Intended Audience :: Science/Research
Classifier: Topic :: Scientific/Engineering :: Visualization
Classifier: Topic :: Scientific/Engineering :: Electronic Design Automation (EDA)
Classifier: License :: OSI Approved :: MIT License
Classifier: Programming Language :: Python :: 3
Classifier: Programming Language :: Python :: 3.8
Classifier: Programming Language :: Python :: 3.9
Classifier: Programming Language :: Python :: 3.10
Classifier: Programming Language :: Python :: 3.11
Classifier: Programming Language :: Python :: 3.12
Classifier: Operating System :: OS Independent
Requires-Python: >=3.8
License-File: LICENSE
Requires-Dist: numpy>=1.19.0
Requires-Dist: plotly>=5.0.0
Requires-Dist: matplotlib>=3.3.0
Provides-Extra: dev
Requires-Dist: pytest>=6.0; extra == "dev"
Requires-Dist: pytest-cov; extra == "dev"
Requires-Dist: black; extra == "dev"
Requires-Dist: flake8; extra == "dev"
Requires-Dist: mypy; extra == "dev"
Requires-Dist: pre-commit; extra == "dev"
Provides-Extra: docs
Requires-Dist: sphinx>=4.0; extra == "docs"
Requires-Dist: sphinx-rtd-theme; extra == "docs"
Requires-Dist: sphinx-autodoc-typehints; extra == "docs"
Requires-Dist: myst-parser; extra == "docs"
Provides-Extra: performance
Requires-Dist: scipy>=1.7.0; extra == "performance"
Requires-Dist: pandas>=1.3.0; extra == "performance"
Requires-Dist: numba>=0.56.0; extra == "performance"
Provides-Extra: all
Requires-Dist: cap3d-viz[dev,docs,performance]; extra == "all"
Dynamic: author
Dynamic: home-page
Dynamic: license-file
Dynamic: requires-python
